AGIPDF2JSON/PDFParserClass.py
AGIPDF2JSON/__init__.py
AGIPDF2JSON/main.py
AGIpdf2json-1.0.1.dist-info/METADATA
AGIpdf2json-1.0.1.dist-info/WHEEL
AGIpdf2json-1.0.1.dist-info/entry_points.txt
AGIpdf2json-1.0.1.dist-info/top_level.txt
AGIpdf2json-1.0.1.dist-info/RECORD
