Metadata-Version: 2.1
Name: AGIpdf2json
Version: 1.0.1
Summary: This package can help user parse PDF files into text file and JSON file. Additionally, it can help user parse question-answer pairs into a JSONL document in prompt-completion format, that is supported by OpenAI
Author: Mayank Monu
Author-email: mayankmono29@gmail.com
Requires-Dist: pdfplumber
Requires-Dist: click
